{
    "block_hash": "0x6c6174657374",
    "block_number": 2,
    "l1_gas_price": {
        "price_in_fri": "0x0",
        "price_in_wei": "0x2"
    },
    "new_root": "0x57b695c82af81429fdc8966088b0196105dfb5aa22b54cbc86fc95dc3b3ece1",
    "parent_hash": "0x626c6f636b2031",
    "sequencer_address": "0x2",
    "starknet_version": "0.13.2",
    "status": "ACCEPTED_ON_L2",
    "timestamp": 2,
    "transactions": [
        {
            "receipt": {
                "actual_fee": {
                    "amount": "0x0",
                    "unit": "WEI"
                },
                "events": [],
                "execution_resources": {
                    "memory_holes": 5,
                    "pedersen_builtin_applications": 32,
                    "steps": 10
                },
                "execution_status": "SUCCEEDED",
                "finality_status": "ACCEPTED_ON_L2",
                "messages_sent": [],
                "transaction_hash": "0x74786e2033",
                "type": "INVOKE"
            },
            "transaction": {
                "calldata": [],
                "contract_address": "0x636f6e74726163742031",
                "entry_point_selector": "0x0",
                "max_fee": "0x0",
                "signature": [],
                "type": "INVOKE",
                "version": "0x0"
            }
        },
        {
            "receipt": {
                "actual_fee": {
                    "amount": "0x0",
                    "unit": "WEI"
                },
                "events": [],
                "execution_resources": {
                    "memory_holes": 5,
                    "pedersen_builtin_applications": 32,
                    "steps": 10
                },
                "execution_status": "SUCCEEDED",
                "finality_status": "ACCEPTED_ON_L2",
                "messages_sent": [],
                "transaction_hash": "0x74786e2034",
                "type": "INVOKE"
            },
            "transaction": {
                "calldata": [],
                "contract_address": "0x0",
                "entry_point_selector": "0x0",
                "max_fee": "0x0",
                "signature": [],
                "type": "INVOKE",
                "version": "0x0"
            }
        },
        {
            "receipt": {
                "actual_fee": {
                    "amount": "0x0",
                    "unit": "WEI"
                },
                "events": [],
                "execution_resources": {
                    "memory_holes": 5,
                    "pedersen_builtin_applications": 32,
                    "steps": 10
                },
                "execution_status": "SUCCEEDED",
                "finality_status": "ACCEPTED_ON_L2",
                "messages_sent": [],
                "transaction_hash": "0x74786e2035",
                "type": "INVOKE"
            },
            "transaction": {
                "calldata": [],
                "contract_address": "0x636f6e74726163742031",
                "entry_point_selector": "0x0",
                "max_fee": "0x0",
                "signature": [],
                "type": "INVOKE",
                "version": "0x0"
            }
        },
        {
            "receipt": {
                "actual_fee": {
                    "amount": "0x0",
                    "unit": "FRI"
                },
                "events": [],
                "execution_resources": {
                    "memory_holes": 5,
                    "pedersen_builtin_applications": 32,
                    "steps": 10
                },
                "execution_status": "SUCCEEDED",
                "finality_status": "ACCEPTED_ON_L2",
                "messages_sent": [
                    {
                        "from_address": "0xcafebabe",
                        "payload": [
                            "0x1",
                            "0x2",
                            "0x3"
                        ],
                        "to_address": "0x0"
                    }
                ],
                "transaction_hash": "0x74786e2036",
                "type": "INVOKE"
            },
            "transaction": {
                "account_deployment_data": [],
                "calldata": [],
                "fee_data_availability_mode": "L1",
                "nonce": "0x0",
                "nonce_data_availability_mode": "L1",
                "paymaster_data": [],
                "resource_bounds": {
                    "l1_gas": {
                        "max_amount": "0x0",
                        "max_price_per_unit": "0x0"
                    },
                    "l2_gas": {
                        "max_amount": "0x0",
                        "max_price_per_unit": "0x0"
                    }
                },
                "sender_address": "0x636f6e74726163742032202873696572726129",
                "signature": [],
                "tip": "0x0",
                "type": "INVOKE",
                "version": "0x3"
            }
        },
        {
            "receipt": {
                "actual_fee": {
                    "amount": "0x0",
                    "unit": "WEI"
                },
                "events": [],
                "execution_resources": {
                    "memory_holes": 5,
                    "pedersen_builtin_applications": 32,
                    "steps": 10
                },
                "execution_status": "REVERTED",
                "finality_status": "ACCEPTED_ON_L2",
                "messages_sent": [],
                "revert_reason": "Reverted because",
                "transaction_hash": "0x74786e207265766572746564",
                "type": "INVOKE"
            },
            "transaction": {
                "calldata": [],
                "contract_address": "0x636f6e74726163742031",
                "entry_point_selector": "0x0",
                "max_fee": "0x0",
                "signature": [],
                "type": "INVOKE",
                "version": "0x0"
            }
        }
    ]
}
